{
    "763854419484999722": {
        "bal": 1000000,
        "income": 0,
        "prestige": 0,
        "prestige tokens": 0,
        "pending income": 0,
        "income max": 10000000,
        "multi": 0,
        "inventory": {
            "farm": 2,
            "cow_farm": 0,
            "golden_cow_farm": 0,
            "magical_cow_land": 0,
            "white_house_cow": 0,
            "polish_cow": 0,
            "cow_scammer": 0,
            "robber_cow": 0,
            "president_cow": 0,
            "x2space": 0
        }
    }
}